CTADIRAC/__init__.py
CTADIRAC/_version.py
CTADIRAC/version.py
CTADIRAC/ConfigurationSystem/ConfigTemplate.cfg
CTADIRAC/ConfigurationSystem/__init__.py
CTADIRAC/ConfigurationSystem/Agent/StorageMonitorAgent.py
CTADIRAC/ConfigurationSystem/Agent/__init__.py
CTADIRAC/Core/__init__.py
CTADIRAC/Core/Utilities/SoftwareManager.py
CTADIRAC/Core/Utilities/__init__.py
CTADIRAC/Core/Utilities/return_values.py
CTADIRAC/Core/Utilities/tool_box.py
CTADIRAC/Core/Utilities/typer_callbacks.py
CTADIRAC/Core/Workflow/__init__.py
CTADIRAC/Core/Workflow/Modules/ProdDataManager.py
CTADIRAC/Core/Workflow/Modules/__init__.py
CTADIRAC/Core/scripts/__init__.py
CTADIRAC/Core/scripts/cta_dms_check_lfn.py
CTADIRAC/Core/scripts/cta_job_get_parameter.py
CTADIRAC/Core/scripts/cta_prod_add_dataset.py
CTADIRAC/Core/scripts/cta_prod_add_file.py
CTADIRAC/Core/scripts/cta_prod_add_prov.py
CTADIRAC/Core/scripts/cta_prod_check_replicas.py
CTADIRAC/Core/scripts/cta_prod_create_dataset_description.py
CTADIRAC/Core/scripts/cta_prod_create_evndisp_dataset_description.py
CTADIRAC/Core/scripts/cta_prod_dump_dataset.py
CTADIRAC/Core/scripts/cta_prod_failure_monitor.py
CTADIRAC/Core/scripts/cta_prod_find_datasets.py
CTADIRAC/Core/scripts/cta_prod_fix_nsb.py
CTADIRAC/Core/scripts/cta_prod_get_file.py
CTADIRAC/Core/scripts/cta_prod_get_file_by_query.py
CTADIRAC/Core/scripts/cta_prod_get_file_size.py
CTADIRAC/Core/scripts/cta_prod_get_merge_size.py
CTADIRAC/Core/scripts/cta_prod_get_replicas.py
CTADIRAC/Core/scripts/cta_prod_get_se_status.py
CTADIRAC/Core/scripts/cta_prod_git_clone.py
CTADIRAC/Core/scripts/cta_prod_init_prov.py
CTADIRAC/Core/scripts/cta_prod_managedata.py
CTADIRAC/Core/scripts/cta_prod_mark_corrupted_DL0.py
CTADIRAC/Core/scripts/cta_prod_monitor.py
CTADIRAC/Core/scripts/cta_prod_remove_corrupted_dl2.py
CTADIRAC/Core/scripts/cta_prod_remove_corrupted_file.py
CTADIRAC/Core/scripts/cta_prod_remove_dataset.py
CTADIRAC/Core/scripts/cta_prod_remove_file.py
ctadirac-3.0.7.dist-info/licenses/LICENCE
ctadirac-3.0.7.dist-info/METADATA
ctadirac-3.0.7.dist-info/WHEEL
ctadirac-3.0.7.dist-info/entry_points.txt
ctadirac-3.0.7.dist-info/top_level.txt
ctadirac-3.0.7.dist-info/RECORD
