Metadata-Version: 2.4
Name: CTADIRAC
Version: 3.0.7
Summary: CTADIRAC is an extension of the DIRAC interware for dedicated CTA usage.
Author-email: Luisa Arrabito <arrabito@in2p3.fr>
License: BSD 3-Clause License
Project-URL: Homepage, https://gitlab.cta-observatory.org/cta-computing/dpps/CTADIRAC/
Project-URL: Issues, https://gitlab.cta-observatory.org/cta-computing/dpps/CTADIRAC/-/issues
Project-URL: Repository, https://gitlab.cta-observatory.org/cta-computing/dpps/CTADIRAC.git
Keywords: DIRAC,CTA,Workflow,GridComputing
Classifier: Intended Audience :: Science/Research
Classifier: Programming Language :: Python :: 3
Classifier: Topic :: Scientific/Engineering
Classifier: Topic :: System :: Distributed Computing
Requires-Python: >=3.9
License-File: LICENCE
Requires-Dist: DIRAC==9.0.14
Requires-Dist: ruamel.yaml
Requires-Dist: shellescape
Requires-Dist: matplotlib
Requires-Dist: typer[all]
Provides-Extra: test
Requires-Dist: pytest; extra == "test"
Requires-Dist: pytest-cov; extra == "test"
Requires-Dist: codecov; extra == "test"
Requires-Dist: flake8; extra == "test"
Requires-Dist: pytest-xdist; extra == "test"
Requires-Dist: mock; extra == "test"
Provides-Extra: server
Requires-Dist: DIRAC[server]==9.0.14; extra == "server"
Dynamic: license-file
